Metadata-Version: 1.1
Name: burst-detection
Version: 0.1.3
Summary: Detect bursts in batched data using Kleinbergs (2002) algorithm.
Home-page: http://github.com/nmarinsek/burst_detection
Author: Nikki Marinsek
Author-email: nikki.marinsek@gmail.com
License: UNKNOWN
Keywords: bursts burst bursty time series fads trends kleinberg streams timecourse
Platform: UNKNOWN
Classifier: Intended Audience :: Science/Research
Classifier: License :: Free for non-commercial use
Classifier: Programming Language :: Python
Classifier: Topic :: Scientific/Engineering :: Information Analysis
Classifier: Topic :: Software Development :: Libraries :: Python Modules
